[
	{
		"element":     "InputText",
		"description": "FORM-INPUT of type text",
		"eltype":      "text",

		"fixedProps":    [
		  { "prop": "name"        , "typ": "text",     "disp": "String",  "def": "" },
		  { "prop": "label"       , "typ": "text",     "disp": "String",  "def": "" },
		  { "prop": "placeholder" , "typ": "text",     "disp": "String",  "def": "" },
		  { "prop": "readonly"    , "typ": "checkbox", "disp": "Boolean", "def": false },
		  { "prop": "required"    , "typ": "checkbox", "disp": "Boolean", "def": false }
		],

		"variableProps": [
		  { "prop": "maxlength"   , "typ": "number", "disp": "Number", "def": 100 }
		],
		"status": false 
	  
	},
	{
		"element":     "InputNumber",
		"description": "FORM-INPUT of type number",
		"eltype":      "number",

		"fixedProps":    [
		  { "prop": "name"        , "typ": "text",     "disp": "String",  "def": "" },
		  { "prop": "label"       , "typ": "text",     "disp": "String",  "def": "" },
		  { "prop": "placeholder" , "typ": "text",     "disp": "String",  "def": "" },
		  { "prop": "readonly"    , "typ": "checkbox", "disp": "Boolean", "def": false },
		  { "prop": "required"    , "typ": "checkbox", "disp": "Boolean", "def": false }
		],

		"variableProps": [
		  { "prop": "min"         , "typ": "number", "disp": "Number", "def": 0 },
		  { "prop": "max"         , "typ": "number", "disp": "Number", "def": 100 },
		  { "prop": "step"        , "typ": "number", "disp": "Number", "def": 1 }
		],
		"status": false 
	},
	{
		"element":     "InputColor",
		"description": "FORM-INPUT of type color",
		"eltype":      "color",

		"fixedProps":    [
		  { "prop": "name"        , "typ": "text",     "disp": "String",  "def": "" },
		  { "prop": "label"       , "typ": "text",     "disp": "String",  "def": "" },
		  { "prop": "placeholder" , "typ": "text",     "disp": "String",  "def": "" },
		  { "prop": "readonly"    , "typ": "checkbox", "disp": "Boolean", "def": false },
		  { "prop": "required"    , "typ": "checkbox", "disp": "Boolean", "def": false }
		],

		"variableProps": [
		  { "prop": "color"       , "typ": "color", "disp": "Color", "def": "#0000000" }
		],
		"status": false 
	},
	{  
		"element":     "InputCheckBox",
		"description": "FORM-INPUT of type checkbox",
		"eltype":      "checkbox",

		"fixedProps":    [
		  { "prop": "name"        , "typ": "text",     "disp": "String",  "def": "" },
		  { "prop": "label"       , "typ": "text",     "disp": "String",  "def": "" },
		  { "prop": "placeholder" , "typ": "text",     "disp": "String",  "def": "" },
		  { "prop": "readonly"    , "typ": "checkbox", "disp": "Boolean", "def": false },
		  { "prop": "required"    , "typ": "checkbox", "disp": "Boolean", "def": false }
		],

		"variableProps": [
		  { "prop": "checked"     , "typ": "checkbox", "def": false }
		],
		"status": false 
	},
	{
		"element":     "InputTextArea",
		"description": "FORM-INPUT of type textarea",
		"eltype":      "textarea",

		"fixedProps":    [
		  { "prop": "name"        , "typ": "text",     "disp": "String",  "def": "" },
		  { "prop": "label"       , "typ": "text",     "disp": "String",  "def": "" },
		  { "prop": "placeholder" , "typ": "text",     "disp": "String",  "def": "" },
		  { "prop": "readonly"    , "typ": "checkbox", "disp": "Boolean", "def": false },
		  { "prop": "required"    , "typ": "checkbox", "disp": "Boolean", "def": false }
		],

		"variableProps": [
		  { "prop": "maxlength"   , "typ": "number", "disp": "Number", "def": 100 },
		  { "prop": "wrap"        , "typ": "text",   "disp": "String", "def": "soft" }
		],
		"status": false
	}
]